adafruit_boardtest/__init__.py
adafruit_boardtest/boardtest_gpio.py
adafruit_boardtest/boardtest_i2c.py
adafruit_boardtest/boardtest_led.py
adafruit_boardtest/boardtest_sd.py
adafruit_boardtest/boardtest_sd_cd.py
adafruit_boardtest/boardtest_spi.py
adafruit_boardtest/boardtest_uart.py
adafruit_boardtest/boardtest_voltage_monitor.py
adafruit_circuitpython_boardtest-1.2.25.dist-info/licenses/LICENSE
adafruit_circuitpython_boardtest-1.2.25.dist-info/METADATA
adafruit_circuitpython_boardtest-1.2.25.dist-info/WHEEL
adafruit_circuitpython_boardtest-1.2.25.dist-info/top_level.txt
adafruit_circuitpython_boardtest-1.2.25.dist-info/RECORD
